text2story/__init__.py
text2story/__main__.py
text2story/annotators/__init__.py
text2story/annotators/ALLENNLP/PropBankBr.py
text2story/annotators/ALLENNLP/__init__.py
text2story/annotators/ALLENNLP/allen_wrapper.py
text2story/annotators/ALLENNLP/my_model.py
text2story/annotators/ALLENNLP/my_reader.py
text2story/annotators/ALLENNLP/preprocess.py
text2story/annotators/ALLENNLP/requirements.txt
text2story/annotators/ALLENNLP/Models/srl-pt_bertimbau-base/config.json
text2story/annotators/ALLENNLP/Models/srl-pt_bertimbau-base/linear_layer.pt
text2story/annotators/ALLENNLP/Models/srl-pt_bertimbau-base/Vocabulary/labels.txt
text2story/annotators/ALLENNLP/Models/srl-pt_bertimbau-base/Vocabulary/non_padded_namespaces.txt
text2story/annotators/BERTNERPT/POS_tagger_brill.pkl
text2story/annotators/BERTNERPT/__init__.py
text2story/annotators/CUSTOMPT/__init__.py
text2story/annotators/CUSTOMPT/crf_v2.1.joblib
text2story/annotators/CUSTOMPT/event_model.py
text2story/annotators/CUSTOMPT/feature_extractor.py
text2story/annotators/DBPEDIA/__init__.py
text2story/annotators/LUSA/__init__.py
text2story/annotators/MAVERICK/__init__.py
text2story/annotators/NLTK/__init__.py
text2story/annotators/PY_HEIDELTIME/__init__.py
text2story/annotators/SPACY/__init__.py
text2story/annotators/SPARKNLP/__init__.py
text2story/annotators/SRL/__init__.py
text2story/annotators/SRL/evaluator.py
text2story/annotators/SRL/srl_pipeline.py
text2story/annotators/SRL/srl_model/__init__.py
text2story/annotators/SRL/srl_model/config.py
text2story/annotators/SRL/srl_model/model.py
text2story/annotators/SRLWeakLabeling/__init__.py
text2story/annotators/TEI2GO/__init__.py
text2story/brat2viz/README.md
text2story/brat2viz/__init__.py
text2story/brat2viz/brat.py
text2story/brat2viz/drs.py
text2story/brat2viz/brat2drs/README.md
text2story/brat2viz/brat2drs/__init__.py
text2story/brat2viz/brat2drs/brat2drs.py
text2story/brat2viz/brat2drs/files_monitor.py
text2story/brat2viz/brat2drs/temporal_inference_engine.py
text2story-1.6.10.1.dist-info/licenses/LICENSE
text2story-1.6.10.1.dist-info/METADATA
text2story-1.6.10.1.dist-info/WHEEL
text2story-1.6.10.1.dist-info/top_level.txt
text2story-1.6.10.1.dist-info/zip-safe
text2story-1.6.10.1.dist-info/RECORD
