Metadata-Version: 2.4
Name: text2story
Version: 1.6.10.1
Home-page: https://github.com/LIAAD/Text2StoryPackage
License-File: LICENSE
Requires-Dist: joblib
Requires-Dist: importlib_metadata
Requires-Dist: numpy
Requires-Dist: spacy
Requires-Dist: py_heideltime
Requires-Dist: nltk
Requires-Dist: transformers
Requires-Dist: torch
Requires-Dist: pytorch-crf
Requires-Dist: bs4
Requires-Dist: networkx
Requires-Dist: plantuml
Requires-Dist: pandas
Requires-Dist: spacy-transformers
Requires-Dist: evaluate
Requires-Dist: matplotlib
Requires-Dist: netgraph
Requires-Dist: maverick-coref
Requires-Dist: spacy-curated-transformers
Requires-Dist: omegaconf
Dynamic: license-file
